CalCalc/CalCalc.py
CalCalc/__init__.py
CalCalc_nicole-0.0.1.dist-info/LICENSE.txt
CalCalc_nicole-0.0.1.dist-info/METADATA
CalCalc_nicole-0.0.1.dist-info/WHEEL
CalCalc_nicole-0.0.1.dist-info/top_level.txt
CalCalc_nicole-0.0.1.dist-info/RECORD
